rvit/__init__.py
rvit/registered_vision_transformer.py
rvit-1.0.3.dist-info/METADATA
rvit-1.0.3.dist-info/WHEEL
rvit-1.0.3.dist-info/top_level.txt
rvit-1.0.3.dist-info/RECORD
