Metadata-Version: 2.1
Name: rvit
Version: 1.0.3
Summary: Vision Transformer with Registers
Author: Joe Griffith
Author-email: <joeagriffith@gmail.com
Keywords: python,pytorch,vision transformer,register,registers
Classifier: Development Status :: 5 - Production/Stable
Classifier: Intended Audience :: Science/Research
Classifier: Programming Language :: Python :: 3
Classifier: Operating System :: Unix
Classifier: Operating System :: MacOS :: MacOS X
Classifier: Operating System :: Microsoft :: Windows
Requires-Dist: torch
Requires-Dist: torchvision
